kanjex/__init__.py
kanjex/conjugator.py
kanjex/conjugation/__init__.py
kanjex/conjugation/forms.py
kanjex/conjugation/godan.py
kanjex/conjugation/ichidan.py
kanjex/conjugation/irregular.py
kanjex/unit_tests/__init__.py
kanjex/unit_tests/test_godan.py
kanjex/unit_tests/test_ichidan.py
kanjex/unit_tests/test_irregular.py
kanjex/unit_tests/test_verbs.py
kanjex-0.1.dist-info/METADATA
kanjex-0.1.dist-info/WHEEL
kanjex-0.1.dist-info/top_level.txt
kanjex-0.1.dist-info/RECORD
