Metadata-Version: 2.1
Name: kanjex
Version: 0.1
Summary: Kanji exploration tools.
Home-page: https://github.com/verbose-void/kanji-explorer
Author: Dyllan McCreary
Author-email: dyllanmccreary@gmail.com
